seroflow/__init__.py
seroflow/seroflow.py
seroflow/cache/__init__.py
seroflow/cache/abstract_cache.py
seroflow/cache/lfu_cache.py
seroflow/chunker/__init__.py
seroflow/chunker/chunker.py
seroflow/chunker/direct_chunker.py
seroflow/chunker/distributed_chunker.py
seroflow/context/__init__.py
seroflow/context/context.py
seroflow/engine/__init__.py
seroflow/engine/engine.py
seroflow/engine/pyodbc_engine.py
seroflow/engine/sqlalchemy_engine.py
seroflow/engine/universal_engine.py
seroflow/exceptions/__init__.py
seroflow/exceptions/exception.py
seroflow/extract/__init__.py
seroflow/extract/csv_extractor.py
seroflow/extract/excel_extractor.py
seroflow/extract/extractor.py
seroflow/extract/file_extractor.py
seroflow/extract/odbc_extractor.py
seroflow/extract/sqlserver_extractor.py
seroflow/load/__init__.py
seroflow/load/csv_loader.py
seroflow/load/excel_loader.py
seroflow/load/file_loader.py
seroflow/load/loader.py
seroflow/load/odbc_loader.py
seroflow/load/sqlserver_loader.py
seroflow/log/__init__.py
seroflow/log/logger.py
seroflow/step/__init__.py
seroflow/step/base_step.py
seroflow/step/step.py
seroflow/transform/__init__.py
seroflow/transform/aggregation.py
seroflow/transform/cache.py
seroflow/transform/column.py
seroflow/transform/dataframe.py
seroflow/transform/date.py
seroflow/transform/display.py
seroflow/transform/execution.py
seroflow/transform/index.py
seroflow/transform/internal.py
seroflow/transform/sql.py
seroflow/transform/string.py
seroflow/transform/transformation.py
seroflow/transform/variable.py
seroflow/types/__init__.py
seroflow/types/type_validation.py
seroflow/utils/__init__.py
seroflow/utils/utils.py
seroflow/wrappers/__init__.py
seroflow/wrappers/wrappers.py
seroflow-1.0.0.dist-info/licenses/LICENSE
seroflow-1.0.0.dist-info/METADATA
seroflow-1.0.0.dist-info/WHEEL
seroflow-1.0.0.dist-info/top_level.txt
seroflow-1.0.0.dist-info/RECORD
