Metadata-Version: 2.4
Name: seroflow
Version: 1.0.0
Summary: Seroflow is a Python package designed to help users build and execute efficient data pipelines.
Author-email: Frank Siyung Cho <siyungcho@gmail.com>
License: MIT License
Project-URL: Homepage, https://github.com/SiyungCho/seroflow
Requires-Python: >=3.7
License-File: LICENSE
Requires-Dist: pandas
Requires-Dist: sqlalchemy
Requires-Dist: pyodbc
Requires-Dist: pandasql
Requires-Dist: dill
Requires-Dist: xlrd
Requires-Dist: tqdm
Requires-Dist: pylint
Requires-Dist: openpyxl
Dynamic: license-file
